[{"name":"Денис","surname":"Скворцов","lastName":"Юрьевич","contacts":[{"type":"vk","value":"@vk_skvortsov"},{"type":"fb","value":"@fb_skvortsov"},{"type":"phone","value":"9061234566"},{"type":"mail","value":"skvortsov@gmail.ru"},{"type":"other","value":"Другой контакт 1"},{"type":"other","value":"Другой контакт 2"},{"type":"other","value":"Другой контакт 3"},{"type":"other","value":"Другой контакт 4"},{"type":"other","value":"Другой контакт 5"},{"type":"other","value":"Другой контакт 6"}],"id":"1658210162714","updatedAt":"2022-07-19T05:56:02.842Z","createdAt":"2022-07-19T05:56:02.842Z"},{"name":"Арсений","surname":"Куприянов","lastName":"Валерьевич","contacts":[{"type":"phone","value":"9609998823"},{"type":"mail","value":"kupriyanov@yandex.ru"}],"id":"1658210303632","updatedAt":"2022-07-19T05:58:23.632Z","createdAt":"2022-07-19T05:58:23.632Z"},{"name":"Людмила","surname":"Константинова","lastName":"Александровна","contacts":[],"id":"1658210334672","updatedAt":"2022-07-19T05:58:54.672Z","createdAt":"2022-07-19T05:58:54.672Z"},{"name":"Олег","surname":"Дмитриевский","lastName":"Алексеевич","contacts":[{"type":"phone","value":"9552376899"}],"id":"1658210363905","updatedAt":"2022-07-19T05:59:23.905Z","createdAt":"2022-07-19T05:59:23.905Z"},{"name":"Татьяна","surname":"Александрова","lastName":"Павловна","contacts":[{"type":"vk","value":"@vk_aleksandrova"},{"type":"fb","value":"@fb_aleksandrova"},{"type":"phone","value":"9031234567"}],"id":"1658210406923","updatedAt":"2022-07-19T06:00:47.298Z","createdAt":"2022-07-19T06:00:06.923Z"}]